Metadata-Version: 1.1
Name: pippofc
Version: 0.0.5
Summary: An italian fiscal code calculator
Home-page: UNKNOWN
Author: ImVenomDev
Author-email: imthetruevenom@gmail.com
License: MIT
Keywords: fiscal code
Platform: UNKNOWN
Classifier: Development Status :: 5 - Production/Stable
Classifier: Intended Audience :: Education
Classifier: Operating System :: Microsoft :: Windows :: Windows 10
Classifier: License :: OSI Approved :: MIT License
Classifier: Programming Language :: Python :: 3
